{
  "document": {
    "id": "0:0",
    "name": "Document",
    "type": "DOCUMENT",
    "children": [
      {
        "id": "0:1",
        "name": "Page 1",
        "type": "CANVAS",
        "children": [
          {
            "id": "2:2",
            "name": "공유하기",
            "type": "FRAME",
            "blendMode": "PASS_THROUGH",
            "children": [
              {
                "id": "2:3049",
                "name": "카드",
                "type": "FRAME",
                "blendMode": "PASS_THROUGH",
                "children": [
                  {
                    "id": "2:3050",
                    "name": "썸네일",
                    "type": "FRAME",
                    "blendMode": "PASS_THROUGH",
                    "children": [
                      {
                        "id": "3:909",
                        "name": "Thumbnail / Image-thumbnail",
                        "type": "FRAME",
                        "blendMode": "PASS_THROUGH",
                        "children": [
                          {
                            "id": "3:910",
                            "name": "image",
                            "type": "RECTANGLE",
                            "blendMode": "PASS_THROUGH",
                            "absoluteBoundingBox": {
                              "x": 16,
                              "y": 16,
                              "width": 96,
                              "height": 96
                            },
                            "constraints": {
                              "vertical": "SCALE",
                              "horizontal": "SCALE"
                            },
                            "fills": [
                              {
                                "blendMode": "NORMAL",
                                "type": "IMAGE",
                                "scaleMode": "FILL",
                                "imageRef": "1afb4afb4b637264dac1d543ba3ed1f76277aeb1"
                              }
                            ],
                            "strokes": [],
                            "strokeWeight": 0,
                            "strokeAlign": "CENTER",
                            "effects": [],
                            "cornerRadius": 2
                          },
                          {
                            "id": "3:911",
                            "name": "opacity",
                            "type": "RECTANGLE",
                            "locked": true,
                            "blendMode": "PASS_THROUGH",
                            "absoluteBoundingBox": {
                              "x": 16,
                              "y": 16,
                              "width": 96,
                              "height": 96
                            },
                            "constraints": {
                              "vertical": "SCALE",
                              "horizontal": "SCALE"
                            },
                            "fills": [
                              {
                                "opacity": 0.029999999329447746,
                                "blendMode": "NORMAL",
                                "type": "SOLID",
                                "color": {
                                  "r": 0,
                                  "g": 0,
                                  "b": 0,
                                  "a": 1
                                }
                              }
                            ],
                            "strokes": [],
                            "strokeWeight": 0,
                            "strokeAlign": "CENTER",
                            "effects": [],
                            "cornerRadius": 4
                          }
                        ],
                        "absoluteBoundingBox": {
                          "x": 16,
                          "y": 16,
                          "width": 96,
                          "height": 96
                        },
                        "constraints": {
                          "vertical": "TOP",
                          "horizontal": "LEFT"
                        },
                        "layoutAlign": "INHERIT",
                        "layoutGrow": 0,
                        "clipsContent": true,
                        "background": [
                          {
                            "blendMode": "NORMAL",
                            "type": "SOLID",
                            "color": {
                              "r": 1,
                              "g": 1,
                              "b": 1,
                              "a": 1
                            }
                          }
                        ],
                        "fills": [
                          {
                            "blendMode": "NORMAL",
                            "type": "SOLID",
                            "color": {
                              "r": 1,
                              "g": 1,
                              "b": 1,
                              "a": 1
                            }
                          }
                        ],
                        "strokes": [],
                        "cornerRadius": 4,
                        "strokeWeight": 1,
                        "strokeAlign": "INSIDE",
                        "backgroundColor": {
                          "r": 1,
                          "g": 1,
                          "b": 1,
                          "a": 1
                        },
                        "styles": {
                          "fills": "2:351"
                        },
                        "effects": []
                      }
                    ],
                    "absoluteBoundingBox": {
                      "x": 16,
                      "y": 16,
                      "width": 96,
                      "height": 96
                    },
                    "constraints": {
                      "vertical": "TOP",
                      "horizontal": "LEFT"
                    },
                    "layoutAlign": "INHERIT",
                    "layoutGrow": 0,
                    "clipsContent": false,
                    "background": [],
                    "fills": [],
                    "strokes": [],
                    "strokeWeight": 1,
                    "strokeAlign": "INSIDE",
                    "backgroundColor": {
                      "r": 0,
                      "g": 0,
                      "b": 0,
                      "a": 0
                    },
                    "layoutMode": "VERTICAL",
                    "effects": []
                  },
                  {
                    "id": "2:3053",
                    "name": "상품정보",
                    "type": "FRAME",
                    "blendMode": "PASS_THROUGH",
                    "children": [
                      {
                        "id": "2:3054",
                        "name": "로고 / 시간 / 상품명",
                        "type": "FRAME",
                        "blendMode": "PASS_THROUGH",
                        "children": [
                          {
                            "id": "3:908",
                            "name": "텍스트",
                            "type": "TEXT",
                            "blendMode": "PASS_THROUGH",
                            "absoluteBoundingBox": {
                              "x": 122,
                              "y": 16,
                              "width": 222,
                              "height": 44
                            },
                            "constraints": {
                              "vertical": "SCALE",
                              "horizontal": "CENTER"
                            },
                            "layoutAlign": "INHERIT",
                            "layoutGrow": 1,
                            "fills": [
                              {
                                "blendMode": "NORMAL",
                                "type": "SOLID",
                                "color": {
                                  "r": 0.20000000298023224,
                                  "g": 0.20000000298023224,
                                  "b": 0.20000000298023224,
                                  "a": 1
                                }
                              }
                            ],
                            "strokes": [],
                            "strokeWeight": 0,
                            "strokeAlign": "CENTER",
                            "styles": {
                              "fill": "2:1999"
                            },
                            "effects": [],
                            "characters": "KARRA (77까지)라운드버튼바람막이집업점퍼_KB...",
                            "style": {
                              "fontFamily": "Apple SD Gothic Neo",
                              "fontPostScriptName": "AppleSDGothicNeo-Regular",
                              "fontWeight": 400,
                              "fontSize": 16,
                              "textAlignHorizontal": "LEFT",
                              "textAlignVertical": "TOP",
                              "letterSpacing": -0.4000000059604645,
                              "lineHeightPx": 22,
                              "lineHeightPercent": 117.33332824707031,
                              "lineHeightPercentFontSize": 137.5,
                              "lineHeightUnit": "PIXELS"
                            },
                            "layoutVersion": 3,
                            "characterStyleOverrides": [],
                            "styleOverrideTable": {},
                            "lineTypes": ["NONE"],
                            "lineIndentations": [0]
                          }
                        ],
                        "absoluteBoundingBox": {
                          "x": 122,
                          "y": 16,
                          "width": 222,
                          "height": 44
                        },
                        "constraints": {
                          "vertical": "TOP",
                          "horizontal": "LEFT"
                        },
                        "layoutAlign": "INHERIT",
                        "layoutGrow": 0,
                        "clipsContent": false,
                        "background": [],
                        "fills": [],
                        "strokes": [],
                        "strokeWeight": 1,
                        "strokeAlign": "INSIDE",
                        "backgroundColor": {
                          "r": 0,
                          "g": 0,
                          "b": 0,
                          "a": 0
                        },
                        "layoutMode": "VERTICAL",
                        "itemSpacing": 4,
                        "effects": []
                      },
                      {
                        "id": "2:3059",
                        "name": "가격",
                        "type": "FRAME",
                        "blendMode": "PASS_THROUGH",
                        "children": [
                          {
                            "id": "3:916",
                            "name": "텍스트",
                            "type": "TEXT",
                            "blendMode": "PASS_THROUGH",
                            "absoluteBoundingBox": {
                              "x": 122,
                              "y": 68,
                              "width": 34,
                              "height": 22
                            },
                            "constraints": {
                              "vertical": "SCALE",
                              "horizontal": "SCALE"
                            },
                            "layoutAlign": "INHERIT",
                            "layoutGrow": 0,
                            "fills": [
                              {
                                "blendMode": "NORMAL",
                                "type": "SOLID",
                                "color": {
                                  "r": 0.9415654540061951,
                                  "g": 0.38021349906921387,
                                  "b": 0.15755444765090942,
                                  "a": 1
                                }
                              }
                            ],
                            "strokes": [],
                            "strokeWeight": 0,
                            "strokeAlign": "CENTER",
                            "styles": {
                              "fill": "2:3015"
                            },
                            "effects": [],
                            "characters": "32%",
                            "style": {
                              "fontFamily": "Apple SD Gothic Neo",
                              "fontPostScriptName": "AppleSDGothicNeo-Bold",
                              "fontWeight": 700,
                              "textAutoResize": "WIDTH_AND_HEIGHT",
                              "fontSize": 18,
                              "textAlignHorizontal": "LEFT",
                              "textAlignVertical": "TOP",
                              "letterSpacing": -0.4000000059604645,
                              "lineHeightPx": 22,
                              "lineHeightPercent": 104.2962875366211,
                              "lineHeightPercentFontSize": 122.22222137451172,
                              "lineHeightUnit": "PIXELS"
                            },
                            "layoutVersion": 3,
                            "characterStyleOverrides": [],
                            "styleOverrideTable": {},
                            "lineTypes": ["NONE"],
                            "lineIndentations": [0]
                          },
                          {
                            "id": "3:912",
                            "name": "Price/Item",
                            "type": "FRAME",
                            "blendMode": "PASS_THROUGH",
                            "children": [
                              {
                                "id": "3:913",
                                "name": "텍스트",
                                "type": "TEXT",
                                "blendMode": "PASS_THROUGH",
                                "absoluteBoundingBox": {
                                  "x": 160,
                                  "y": 68,
                                  "width": 53,
                                  "height": 22
                                },
                                "constraints": {
                                  "vertical": "CENTER",
                                  "horizontal": "SCALE"
                                },
                                "layoutAlign": "INHERIT",
                                "layoutGrow": 0,
                                "fills": [
                                  {
                                    "blendMode": "NORMAL",
                                    "type": "SOLID",
                                    "color": {
                                      "r": 0,
                                      "g": 0,
                                      "b": 0,
                                      "a": 1
                                    }
                                  }
                                ],
                                "strokes": [],
                                "strokeWeight": 0,
                                "strokeAlign": "CENTER",
                                "styles": {
                                  "fill": "2:1997"
                                },
                                "effects": [],
                                "characters": "39,920",
                                "style": {
                                  "fontFamily": "Apple SD Gothic Neo",
                                  "fontPostScriptName": "AppleSDGothicNeo-Bold",
                                  "fontWeight": 700,
                                  "textAutoResize": "WIDTH_AND_HEIGHT",
                                  "fontSize": 18,
                                  "textAlignHorizontal": "LEFT",
                                  "textAlignVertical": "TOP",
                                  "letterSpacing": -0.4000000059604645,
                                  "lineHeightPx": 22,
                                  "lineHeightPercent": 104.2962875366211,
                                  "lineHeightPercentFontSize": 122.22222137451172,
                                  "lineHeightUnit": "PIXELS"
                                },
                                "layoutVersion": 3,
                                "characterStyleOverrides": [],
                                "styleOverrideTable": {},
                                "lineTypes": ["NONE"],
                                "lineIndentations": [0]
                              },
                              {
                                "id": "3:914",
                                "name": "텍스트",
                                "type": "TEXT",
                                "blendMode": "PASS_THROUGH",
                                "absoluteBoundingBox": {
                                  "x": 213,
                                  "y": 68,
                                  "width": 16,
                                  "height": 22
                                },
                                "constraints": {
                                  "vertical": "CENTER",
                                  "horizontal": "SCALE"
                                },
                                "layoutAlign": "INHERIT",
                                "layoutGrow": 0,
                                "fills": [
                                  {
                                    "blendMode": "NORMAL",
                                    "type": "SOLID",
                                    "color": {
                                      "r": 0,
                                      "g": 0,
                                      "b": 0,
                                      "a": 1
                                    }
                                  }
                                ],
                                "strokes": [],
                                "strokeWeight": 0,
                                "strokeAlign": "CENTER",
                                "styles": {
                                  "fill": "2:1997"
                                },
                                "effects": [],
                                "characters": "원",
                                "style": {
                                  "fontFamily": "Apple SD Gothic Neo",
                                  "fontPostScriptName": "AppleSDGothicNeo-Regular",
                                  "fontWeight": 400,
                                  "textAutoResize": "WIDTH_AND_HEIGHT",
                                  "fontSize": 18,
                                  "textAlignHorizontal": "LEFT",
                                  "textAlignVertical": "TOP",
                                  "letterSpacing": -0.4000000059604645,
                                  "lineHeightPx": 22,
                                  "lineHeightPercent": 104.2962875366211,
                                  "lineHeightPercentFontSize": 122.22222137451172,
                                  "lineHeightUnit": "PIXELS"
                                },
                                "layoutVersion": 3,
                                "characterStyleOverrides": [],
                                "styleOverrideTable": {},
                                "lineTypes": ["NONE"],
                                "lineIndentations": [0]
                              }
                            ],
                            "absoluteBoundingBox": {
                              "x": 160,
                              "y": 68,
                              "width": 69,
                              "height": 22
                            },
                            "constraints": {
                              "vertical": "TOP",
                              "horizontal": "LEFT"
                            },
                            "layoutAlign": "INHERIT",
                            "layoutGrow": 0,
                            "clipsContent": false,
                            "background": [],
                            "fills": [],
                            "strokes": [],
                            "strokeWeight": 1,
                            "strokeAlign": "INSIDE",
                            "backgroundColor": {
                              "r": 0,
                              "g": 0,
                              "b": 0,
                              "a": 0
                            },
                            "layoutMode": "HORIZONTAL",
                            "counterAxisAlignItems": "CENTER",
                            "effects": []
                          }
                        ],
                        "absoluteBoundingBox": {
                          "x": 122,
                          "y": 68,
                          "width": 107,
                          "height": 22
                        },
                        "constraints": {
                          "vertical": "TOP",
                          "horizontal": "LEFT"
                        },
                        "layoutAlign": "INHERIT",
                        "layoutGrow": 0,
                        "clipsContent": false,
                        "background": [],
                        "fills": [],
                        "strokes": [],
                        "strokeWeight": 1,
                        "strokeAlign": "INSIDE",
                        "backgroundColor": {
                          "r": 0,
                          "g": 0,
                          "b": 0,
                          "a": 0
                        },
                        "layoutMode": "HORIZONTAL",
                        "itemSpacing": 4,
                        "counterAxisAlignItems": "CENTER",
                        "effects": []
                      }
                    ],
                    "absoluteBoundingBox": {
                      "x": 122,
                      "y": 16,
                      "width": 222,
                      "height": 74
                    },
                    "constraints": {
                      "vertical": "TOP",
                      "horizontal": "LEFT"
                    },
                    "layoutAlign": "INHERIT",
                    "layoutGrow": 0,
                    "clipsContent": false,
                    "background": [],
                    "fills": [],
                    "strokes": [],
                    "strokeWeight": 1,
                    "strokeAlign": "INSIDE",
                    "backgroundColor": {
                      "r": 0,
                      "g": 0,
                      "b": 0,
                      "a": 0
                    },
                    "layoutMode": "VERTICAL",
                    "itemSpacing": 8,
                    "effects": []
                  }
                ],
                "absoluteBoundingBox": {
                  "x": 16,
                  "y": 16,
                  "width": 328,
                  "height": 96
                },
                "constraints": {
                  "vertical": "TOP",
                  "horizontal": "LEFT"
                },
                "layoutAlign": "INHERIT",
                "layoutGrow": 0,
                "clipsContent": false,
                "background": [],
                "fills": [],
                "strokes": [],
                "strokeWeight": 1,
                "strokeAlign": "INSIDE",
                "backgroundColor": {
                  "r": 0,
                  "g": 0,
                  "b": 0,
                  "a": 0
                },
                "layoutMode": "HORIZONTAL",
                "itemSpacing": 10,
                "effects": []
              },
              {
                "id": "3:2189",
                "name": "Button / Item",
                "type": "FRAME",
                "blendMode": "PASS_THROUGH",
                "children": [
                  {
                    "id": "3:2190",
                    "name": "BASE",
                    "type": "TEXT",
                    "blendMode": "PASS_THROUGH",
                    "absoluteBoundingBox": {
                      "x": 152.5,
                      "y": 139,
                      "width": 55,
                      "height": 22
                    },
                    "constraints": {
                      "vertical": "CENTER",
                      "horizontal": "CENTER"
                    },
                    "layoutAlign": "INHERIT",
                    "layoutGrow": 0,
                    "fills": [
                      {
                        "blendMode": "NORMAL",
                        "type": "SOLID",
                        "color": {
                          "r": 1,
                          "g": 1,
                          "b": 1,
                          "a": 1
                        }
                      }
                    ],
                    "strokes": [],
                    "strokeWeight": 0,
                    "strokeAlign": "CENTER",
                    "styles": {
                      "fill": "2:351"
                    },
                    "effects": [],
                    "characters": "구매하기",
                    "style": {
                      "fontFamily": "Apple SD Gothic Neo",
                      "fontPostScriptName": "AppleSDGothicNeo-Regular",
                      "fontWeight": 400,
                      "textAutoResize": "WIDTH_AND_HEIGHT",
                      "fontSize": 16,
                      "textAlignHorizontal": "CENTER",
                      "textAlignVertical": "CENTER",
                      "letterSpacing": -0.4000000059604645,
                      "lineHeightPx": 22,
                      "lineHeightPercent": 117.33332824707031,
                      "lineHeightPercentFontSize": 137.5,
                      "lineHeightUnit": "PIXELS"
                    },
                    "layoutVersion": 3,
                    "characterStyleOverrides": [],
                    "styleOverrideTable": {},
                    "lineTypes": ["NONE"],
                    "lineIndentations": [0]
                  }
                ],
                "absoluteBoundingBox": {
                  "x": 16,
                  "y": 128,
                  "width": 328,
                  "height": 44
                },
                "constraints": {
                  "vertical": "CENTER",
                  "horizontal": "LEFT"
                },
                "layoutAlign": "STRETCH",
                "layoutGrow": 0,
                "clipsContent": false,
                "background": [
                  {
                    "blendMode": "NORMAL",
                    "type": "SOLID",
                    "color": {
                      "r": 0.9415654540061951,
                      "g": 0.38021349906921387,
                      "b": 0.15755444765090942,
                      "a": 1
                    }
                  }
                ],
                "fills": [
                  {
                    "blendMode": "NORMAL",
                    "type": "SOLID",
                    "color": {
                      "r": 0.9415654540061951,
                      "g": 0.38021349906921387,
                      "b": 0.15755444765090942,
                      "a": 1
                    }
                  }
                ],
                "strokes": [],
                "cornerRadius": 4,
                "strokeWeight": 1,
                "strokeAlign": "INSIDE",
                "backgroundColor": {
                  "r": 0.9415654540061951,
                  "g": 0.38021349906921387,
                  "b": 0.15755444765090942,
                  "a": 1
                },
                "styles": {
                  "fills": "2:3015"
                },
                "layoutMode": "HORIZONTAL",
                "primaryAxisSizingMode": "FIXED",
                "counterAxisAlignItems": "CENTER",
                "primaryAxisAlignItems": "CENTER",
                "paddingLeft": 8,
                "paddingRight": 8,
                "paddingTop": 11,
                "paddingBottom": 11,
                "effects": []
              }
            ],
            "absoluteBoundingBox": {
              "x": 0,
              "y": 0,
              "width": 360,
              "height": 188
            },
            "constraints": {
              "vertical": "TOP",
              "horizontal": "LEFT"
            },
            "clipsContent": true,
            "background": [
              {
                "blendMode": "NORMAL",
                "type": "SOLID",
                "color": {
                  "r": 1,
                  "g": 1,
                  "b": 1,
                  "a": 1
                }
              }
            ],
            "fills": [
              {
                "blendMode": "NORMAL",
                "type": "SOLID",
                "color": {
                  "r": 1,
                  "g": 1,
                  "b": 1,
                  "a": 1
                }
              }
            ],
            "strokes": [],
            "strokeWeight": 1,
            "strokeAlign": "INSIDE",
            "backgroundColor": {
              "r": 1,
              "g": 1,
              "b": 1,
              "a": 1
            },
            "layoutMode": "VERTICAL",
            "itemSpacing": 16,
            "paddingLeft": 16,
            "paddingRight": 16,
            "paddingTop": 16,
            "paddingBottom": 16,
            "effects": []
          }
        ],
        "backgroundColor": {
          "r": 0.8980392217636108,
          "g": 0.8980392217636108,
          "b": 0.8980392217636108,
          "a": 1
        },
        "prototypeStartNodeID": null,
        "flowStartingPoints": [],
        "prototypeDevice": {
          "type": "NONE",
          "rotation": "NONE"
        }
      }
    ]
  },
  "components": {},
  "componentSets": {},
  "schemaVersion": 0,
  "styles": {
    "2:351": {
      "key": "23d9fe8ad1cac7c4521c409b9c6f33be01e0ede6",
      "name": "White",
      "styleType": "FILL",
      "description": ""
    },
    "2:1999": {
      "key": "56c0b8a713eb840e79ec58c1af115ac41e440f5e",
      "name": "Gray800",
      "styleType": "FILL",
      "description": ""
    },
    "2:3015": {
      "key": "5418fb92589ac6deb71d7cfbdb0bb39220fa2143",
      "name": "Orange500",
      "styleType": "FILL",
      "description": ""
    },
    "2:1997": {
      "key": "223c381e611401aed03e56c957b89209999cd3fe",
      "name": "Black",
      "styleType": "FILL",
      "description": ""
    }
  },
  "name": "커머스 상품 상세 공유하기",
  "lastModified": "2022-05-10T04:44:44Z",
  "thumbnailUrl": "https://s3-alpha-sig.figma.com/thumbnails/ec601292-cf57-4ce2-a0bf-ea7494720ade?Expires=1653264000&Signature=TPxw4kMDou74Jjw1ccm2ITPkiE7Tj-cwXNfijklM7cbiLSNYMsdsAjuNnwr9g7AlYuV-Lanxn-w2zccUNcuYDEjvUmBk8NORf3-9Jcm3ihIFTB02UiSw1temAo8Op66Ce01PJVaxHU-Cv6V2aA5bGo~2tdmYR0RNE2YWc2~FxhlnniaZgKwTTrYU3fTiA-8-hmfMTakA69Z8MqPPGfQZyU0-Z~QA2oLQM5NSLfxYHMgKu7JtpPo6hkLP6eWmnWVkQbhfep6V8I8hQcvG~AzNhRaUEGqK6dKPSteR-E8dxlreEB916OuDCPT17iJcWZSI-19y4TkUVeLDCb5z68nQMQ__&Key-Pair-Id=APKAINTVSUGEWH5XD5UA",
  "version": "1850551060",
  "role": "owner",
  "editorType": "figma",
  "linkAccess": "view"
}
